{
	"course_name": "Professional Applications and Frameworks in Web Development",
	"color": "teal",
	"instructor": "David Tang",
	"syllabus": "http://web-app.usc.edu/soc/syllabus/20141/32051.pdf",
	"time": "Tuesdays 5-7:50pm",
	"office_hours": "OHE 530F: Mon 12:30 - 2pm, Wed 5 - 7:30pm",
	"ta": [
		{ "name": "Herman Tran (Grader)", "email": "herman.c.tran@gmail.com" }
	],
	"homework": [
		{
			"name": "Environment setup",
			"type": "NC",
			"due": "1/21",
			"link": "environment-setup",
			"active": 1
		}
	],

	"weeks": [
		{
			"date": "1/14",
			"units": [
				{
					"subject": "Course Introduction",
					"link": ""
				},
				{
					"subject": "Virtual Development Environments w/ Virtual Box and Vagrant",
					"link": "dev-environments"
				},
				{
					"subject": "Command Line (CLI) Basics",
					"link": "command-line-basics"
				},
        {
          "subject": "Slides",
          "link": "https://slid.es/davidtang/virtual-dev-environments"
        }
			],
			"active": 1
		},
    {
      "date": "1/21",
      "units": [
        {
          "subject": "HTTP life cycle",
          "link": ""
        },
        {
          "subject": "SQL review",
          "link": ""
        },
        {
          "subject": "SQL joins",
          "link": "sql-joins"
        },
        {
          "subject": "Object Oriented Programming - part 1",
          "link": "oop-1"
        },
        {
          "subject": "DB driven pages with PDO",
          "link": ""
        },
        {
          "subject": "Version Control w/ Git & Github",
          "link": ""
        }
      ],
      "active": 0
    },
    {
      "date": "1/28",
      "units": [
        {
          "subject": "Object Oriented Programming - part 2",
          "link": ""
        }
      ],
      "active": 0
    },
    {
      "date": "2/4",
      "units": [
        {
          "subject": "Namespacing, autoloading, & dependency management",
          "link": ""
        }
      ],
      "active": 0
    }
	]
}
